{"version":1,"resource":"file:///mnt/data69/Projects/aerOS/v1/releng/pacman.conf","entries":[{"id":"NCW0.conf","timestamp":1683643653696},{"id":"3Ewf.conf","timestamp":1683643681338},{"id":"LpZO.conf","timestamp":1683650819541},{"id":"hNzE.conf","timestamp":1683650852232},{"id":"dbVO.conf","timestamp":1683651295942},{"id":"XYni.conf","timestamp":1683651332102},{"id":"qucs.conf","timestamp":1683651388367},{"id":"CMyQ.conf","timestamp":1683651677875},{"id":"Z5ti.conf","timestamp":1683651742002},{"id":"K62K.conf","timestamp":1683652561115},{"id":"HKtJ.conf","timestamp":1683652632372}]}